biobrigit/__init__.py
biobrigit/__main__.py
biobrigit/biobrigit.py
biobrigit/utils/__init__.py
biobrigit/utils/data.py
biobrigit/utils/layers.py
biobrigit/utils/models.py
biobrigit/utils/pdb_parser.py
biobrigit/utils/scoring.py
biobrigit/utils/tools.py
biobrigit/utils/stats/__init__.py
biobrigit/utils/stats/gaussian_statistics.json
biobrigit/utils/stats/residue_statistics.json
biobrigit/utils/trained_models/BrigitCNN.bak
biobrigit/utils/trained_models/__init__.py
biobrigit-1.0.0.data/data/BrigitCNN.bak
biobrigit-1.0.0.data/data/README.md
biobrigit-1.0.0.data/data/gaussian_statistics.json
biobrigit-1.0.0.data/data/residue_statistics.json
biobrigit-1.0.0.dist-info/licenses/LICENSE
tests/__init__.py
tests/test_brigit.py
biobrigit-1.0.0.dist-info/METADATA
biobrigit-1.0.0.dist-info/WHEEL
biobrigit-1.0.0.dist-info/entry_points.txt
biobrigit-1.0.0.dist-info/top_level.txt
biobrigit-1.0.0.dist-info/RECORD
