Metadata-Version: 2.4
Name: biobrigit
Version: 1.0.0
Summary: Computational tool for the prediction of metal-binding loading paths in proteins using deep convolutional neural networks.
Home-page: https://github.com/insillichem/BioBrigit
Author: Raúl Fernández Díaz
Author-email: raul.fernandezdiaz@ucdconnect.ie
License: BSD license
Keywords: biobrigit
Requires-Python: >=3.6
License-File: LICENSE
Requires-Dist: scikit-learn
Requires-Dist: torch
Requires-Dist: moleculekit==1.8.18
Requires-Dist: lightning
Requires-Dist: pdb2pqr
Dynamic: author
Dynamic: author-email
Dynamic: description
Dynamic: description-content-type
Dynamic: home-page
Dynamic: keywords
Dynamic: license
Dynamic: license-file
Dynamic: requires-dist
Dynamic: requires-python
Dynamic: summary
